nexi/__about__.py
nexi/__init__.py
nexi/__main__.py
nexi/estimate_nexi.py
nexi/estimate_nexi_noiseless.py
nexi/models/__init__.py
nexi/models/microstructure_models.py
nexi/models/nexi.py
nexi/models/nexi_rm.py
nexi/models/functions/__init__.py
nexi/models/functions/nexi_functions.py
nexi/models/functions/rician_mean.py
nexi/models/parameters/__init__.py
nexi/models/parameters/acq_parameters.py
nexi/models/parameters/mist_parameters.py
nexi/models/parameters/save_parameters.py
nexi/nls/__init__.py
nexi/nls/gridsearch.py
nexi/nls/nls.py
nexi/powderaverage/__init__.py
nexi/powderaverage/powderaverage.py
nexi-1.0.7.dist-info/METADATA
nexi-1.0.7.dist-info/WHEEL
nexi-1.0.7.dist-info/licenses/LICENSE
nexi-1.0.7.dist-info/RECORD
